bloxapi/roblox.py
humunaiodio2443-0.3.6.dist-info/licenses/LICENSE
humunaiodio2443-0.3.6.dist-info/METADATA
humunaiodio2443-0.3.6.dist-info/WHEEL
humunaiodio2443-0.3.6.dist-info/top_level.txt
humunaiodio2443-0.3.6.dist-info/RECORD
