Metadata-Version: 2.4
Name: humunaiodio2443
Version: 0.3.6
Summary: Test
Author-email: wangzhou <wangzhou@gmail.com>
Project-URL: Homepage, https://github.com/wangzhou/test
Project-URL: Bug Tracker, https://github.com/wangzhou/test/issues
Classifier: Development Status :: 3 - Alpha
Classifier: Intended Audience :: Developers
Classifier: License :: OSI Approved :: MIT License
Classifier: Operating System :: OS Independent
Classifier: Programming Language :: Python :: 3
Classifier: Programming Language :: Python :: 3.7
Classifier: Programming Language :: Python :: 3.8
Classifier: Programming Language :: Python :: 3.9
Classifier: Programming Language :: Python :: 3.10
Classifier: Programming Language :: Python :: 3.11
Requires-Python: >=3.7
License-File: LICENSE
Requires-Dist: pycryptodome
Requires-Dist: requests>=2.25.0
Dynamic: license-file
